{
  "debugLogging": false,
  "enableFleeFromUnseenAttackerGoal": true,
  "configSchemaVersion": 5,
  "workerThreads": 0,
  "workerQueueCapacity": 1024,
  "workerTaskBudgetMs": 2,
  "asyncSubmitCooldownTicks": 10,
  "asyncResultTtlMs": 2500,
  "soundLifetimeTicks": 200,
  "scanCooldownTicks": 25,
  "minTpsForScanCooldown": 10.0,
  "maxTpsForScanCooldown": 20.0,
  "cellsPerTick": 50,
  "minCellsPerTick": 25,
  "maxCellsPerTick": 100,
  "mobsPerCellPerTick": 55,
  "minMobsPerCellPerTick": 25,
  "maxMobsPerCellPerTick": 100,
  "lastKnownTps": 20.0,
  "useRangeInSoundSwitch": true,
  "soundSwitchRatio": 0.7,
  "soundNoveltyBonusWeight": 0.5,
  "soundNoveltyTimeTicks": 100,
  "arrivalDistance": 6.0,
  "mobMoveSpeed": 1.15,
  "attractedEntities": [
    "minecraft:cave_spider",
    "minecraft:creeper",
    "minecraft:drowned",
    "minecraft:endermite",
    "minecraft:evoker",
    "minecraft:guardian",
    "minecraft:hoglin",
    "minecraft:husk",
    "minecraft:magma_cube",
    "minecraft:phantom",
    "minecraft:piglin",
    "minecraft:piglin_brute",
    "minecraft:pillager",
    "minecraft:ravager",
    "minecraft:shulker",
    "minecraft:silverfish",
    "minecraft:skeleton",
    "minecraft:slime",
    "minecraft:spider",
    "minecraft:stray",
    "minecraft:vex",
    "minecraft:vindicator",
    "minecraft:witch",
    "minecraft:wither_skeleton",
    "minecraft:zoglin",
    "minecraft:zombie",
    "minecraft:zombie_villager"
  ],
  "edgeMobSmartBehavior": false,
  "edgeInvestigateWaitTicks": 15,
  "spatialPartitionSize": 24,
  "groupDistance": 128.0,
  "maxGroupSize": 128,
  "maxLeaders": 16,
  "leaderSpacingMultiplier": 1.0,
  "edgeMobsPerSector": 4,
  "groupSprintMultiplier": 1.1,
  "leaderReturnArrivalDistance": 2.0,
  "groupUpdateInterval": 200,
  "raidCountdownTicks": 200,
  "numEdgeSectors": 6,
  "nonPlayerSoundIdList": [
    "minecraft:item.crossbow.shoot;16;4",
    "minecraft:item.crossbow.loading_start;6;2",
    "minecraft:item.crossbow.loading_middle;6;2",
    "minecraft:item.crossbow.loading_end;6;2",
    "minecraft:item.crossbow.quick_charge_1;6;2",
    "minecraft:item.crossbow.quick_charge_2;6;2",
    "minecraft:item.crossbow.quick_charge_3;6;2",
    "minecraft:entity.arrow.shoot;14;4",
    "minecraft:item.shield.block;12;3",
    "minecraft:block.lever.click;5;3",
    "minecraft:block.wooden_trapdoor.open;8;3",
    "minecraft:block.wooden_trapdoor.close;8;3",
    "minecraft:block.bamboo_wood_trapdoor.open;10;3",
    "minecraft:block.bamboo_wood_trapdoor.close;10;3",
    "minecraft:block.cherry_wood_trapdoor.open;10;3",
    "minecraft:block.cherry_wood_trapdoor.close;10;3",
    "minecraft:block.iron_trapdoor.open;15;4",
    "minecraft:block.iron_trapdoor.close;15;4",
    "minecraft:block.wooden_door.open;12;4",
    "minecraft:block.wooden_door.close;12;4",
    "minecraft:block.bamboo_wood_door.open;15;4",
    "minecraft:block.bamboo_wood_door.close;15;4",
    "minecraft:block.cherry_wood_door.open;15;4",
    "minecraft:block.cherry_wood_door.close;15;4",
    "minecraft:block.iron_door.open;20;5",
    "minecraft:block.iron_door.close;20;5",
    "minecraft:block.fence_gate.open;10;3",
    "minecraft:block.fence_gate.close;10;3",
    "minecraft:block.piston.extend;25;4",
    "minecraft:block.piston.contract;25;4",
    "minecraft:block.dispenser.dispense;12;4",
    "minecraft:block.dispenser.launch;12;4",
    "minecraft:block.anvil.land;45;5",
    "minecraft:block.anvil.use;35;5",
    "minecraft:block.anvil.destroy;30;5",
    "minecraft:block.sand.fall;6;3",
    "minecraft:block.gravel.fall;6;3",
    "minecraft:block.grass.break;3;2",
    "minecraft:block.scaffolding.break;3;2",
    "minecraft:entity.boat.paddle_water;8;3",
    "minecraft:ambient.underwater.enter;4;2",
    "minecraft:ambient.underwater.exit;4;2",
    "minecraft:block.chest.open;5;2",
    "minecraft:block.chest.close;5;2",
    "minecraft:block.barrel.open;5;2",
    "minecraft:block.barrel.close;5;2",
    "minecraft:block.ender_chest.open;6;2",
    "minecraft:block.ender_chest.close;6;2",
    "minecraft:block.shulker_box.open;6;2",
    "minecraft:block.shulker_box.close;6;2",
    "minecraft:block.bell.use;40;5",
    "minecraft:block.bell.resonate;25;4",
    "minecraft:block.furnace.fire_crackle;8;3",
    "minecraft:entity.generic.explode;50;7",
    "minecraft:entity.firework_rocket.launch;10;3",
    "minecraft:entity.firework_rocket.blast;20;5",
    "minecraft:entity.firework_rocket.large_blast;30;6",
    "musketmod:musket_fire;155;8",
    "musketmod:blunderbuss_fire;154;7",
    "musketmod:pistol_fire;164;5",
    "cgm:item.shotgun.fire;156;15",
    "cgm:item.shotgun.silenced_fire;131;13",
    "cgm:item.shotgun.enchanted_fire;156;15",
    "cgm:item.shotgun.cock;90;6",
    "cgm:item.rifle.fire;162;16",
    "cgm:item.rifle.silenced_fire;137;13",
    "cgm:item.rifle.enchanted_fire;162;16",
    "cgm:item.rifle.cock;90;6",
    "cgm:item.pistol.fire;164;16",
    "cgm:item.pistol.silenced_fire;139;13",
    "cgm:item.pistol.enchanted_fire;164;16",
    "cgm:item.pistol.reload;85;7",
    "cgm:item.pistol.cock;90;6",
    "cgm:item.assault_rifle.fire;159;16",
    "cgm:item.assault_rifle.silenced_fire;134;13",
    "cgm:item.assault_rifle.enchanted_fire;159;16",
    "cgm:item.assault_rifle.cock;90;6",
    "cgm:item.grenade_launcher.fire;172;17",
    "cgm:item.bazooka.fire;184;17",
    "cgm:item.mini_gun.fire;180;17",
    "cgm:item.mini_gun.enchanted_fire;180;17",
    "cgm:item.machine_pistol.fire;160;16",
    "cgm:item.machine_pistol.silenced_fire;135;13",
    "cgm:item.machine_pistol.enchanted_fire;160;16",
    "cgm:item.heavy_rifle.fire;165;16",
    "cgm:item.heavy_rifle.silenced_fire;140;13",
    "cgm:item.heavy_rifle.enchanted_fire;165;16",
    "cgm:item.heavy_rifle.cock;90;6",
    "cgm:item.grenade.pin;72;6",
    "cgm:entity.stun_grenade.explosion;175;18",
    "cgm:entity.stun_grenade.ring;104;10"
  ],
  "soundIdWhitelist": [
    "minecraft:item.crossbow.shoot",
    "minecraft:item.crossbow.loading_start",
    "minecraft:item.crossbow.loading_middle",
    "minecraft:item.crossbow.loading_end",
    "minecraft:item.crossbow.quick_charge_1",
    "minecraft:item.crossbow.quick_charge_2",
    "minecraft:item.crossbow.quick_charge_3",
    "minecraft:entity.arrow.shoot",
    "minecraft:item.shield.block",
    "minecraft:block.lever.click",
    "minecraft:block.wooden_trapdoor.open",
    "minecraft:block.wooden_trapdoor.close",
    "minecraft:block.bamboo_wood_trapdoor.open",
    "minecraft:block.bamboo_wood_trapdoor.close",
    "minecraft:block.cherry_wood_trapdoor.open",
    "minecraft:block.cherry_wood_trapdoor.close",
    "minecraft:block.iron_trapdoor.open",
    "minecraft:block.iron_trapdoor.close",
    "minecraft:block.wooden_door.open",
    "minecraft:block.wooden_door.close",
    "minecraft:block.bamboo_wood_door.open",
    "minecraft:block.bamboo_wood_door.close",
    "minecraft:block.cherry_wood_door.open",
    "minecraft:block.cherry_wood_door.close",
    "minecraft:block.iron_door.open",
    "minecraft:block.iron_door.close",
    "minecraft:block.fence_gate.open",
    "minecraft:block.fence_gate.close",
    "minecraft:block.piston.extend",
    "minecraft:block.piston.contract",
    "minecraft:block.dispenser.dispense",
    "minecraft:block.dispenser.launch",
    "minecraft:block.anvil.land",
    "minecraft:block.anvil.use",
    "minecraft:block.anvil.destroy",
    "minecraft:block.sand.fall",
    "minecraft:block.gravel.fall",
    "minecraft:block.grass.break",
    "minecraft:block.scaffolding.break",
    "minecraft:entity.boat.paddle_water",
    "minecraft:ambient.underwater.enter",
    "minecraft:ambient.underwater.exit",
    "minecraft:block.chest.open",
    "minecraft:block.chest.close",
    "minecraft:block.barrel.open",
    "minecraft:block.barrel.close",
    "minecraft:block.ender_chest.open",
    "minecraft:block.ender_chest.close",
    "minecraft:block.shulker_box.open",
    "minecraft:block.shulker_box.close",
    "minecraft:block.bell.use",
    "minecraft:block.furnace.fire_crackle",
    "minecraft:entity.generic.explode",
    "minecraft:entity.firework_rocket.launch",
    "minecraft:entity.firework_rocket.blast",
    "minecraft:entity.firework_rocket.large_blast",
    "minecraft:random/anvil_land",
    "entity/leashknot/place1",
    "minecraft:entity.player.sprint",
    "minecraft:entity.player.jump",
    "minecraft:entity.player.sneak",
    "soundattract:voice_chat",
    "musketmod:musket_fire",
    "musketmod:blunderbuss_fire",
    "musketmod:pistol_fire",
    "cgm:item.shotgun.fire",
    "cgm:item.shotgun.silenced_fire",
    "cgm:item.shotgun.enchanted_fire",
    "cgm:item.shotgun.cock",
    "cgm:item.rifle.fire",
    "cgm:item.rifle.silenced_fire",
    "cgm:item.rifle.enchanted_fire",
    "cgm:item.rifle.cock",
    "cgm:item.pistol.fire",
    "cgm:item.pistol.silenced_fire",
    "cgm:item.pistol.enchanted_fire",
    "cgm:item.pistol.reload",
    "cgm:item.pistol.cock",
    "cgm:item.assault_rifle.fire",
    "cgm:item.assault_rifle.silenced_fire",
    "cgm:item.assault_rifle.enchanted_fire",
    "cgm:item.assault_rifle.cock",
    "cgm:item.grenade_launcher.fire",
    "cgm:item.bazooka.fire",
    "cgm:item.mini_gun.fire",
    "cgm:item.mini_gun.enchanted_fire",
    "cgm:item.machine_pistol.fire",
    "cgm:item.machine_pistol.silenced_fire",
    "cgm:item.machine_pistol.enchanted_fire",
    "cgm:item.heavy_rifle.fire",
    "cgm:item.heavy_rifle.silenced_fire",
    "cgm:item.heavy_rifle.enchanted_fire",
    "cgm:item.heavy_rifle.cock",
    "cgm:item.grenade.pin",
    "cgm:entity.stun_grenade.explosion",
    "cgm:entity.stun_grenade.ring",
    "pointblank:gun_action"
  ],
  "mufflingAreaRadius": 0,
  "woolMufflingEnabled": true,
  "customWoolBlocks": [],
  "woolBlockRangeReduction": 6,
  "woolBlockWeightReduction": 0.6,
  "solidMufflingEnabled": true,
  "customSolidBlocks": [],
  "solidBlockRangeReduction": 4,
  "solidBlockWeightReduction": 0.4,
  "nonSolidMufflingEnabled": true,
  "customNonSolidBlocks": [],
  "nonSolidBlockRangeReduction": 3,
  "nonSolidBlockWeightReduction": 0.3,
  "thinMufflingEnabled": true,
  "customThinBlocks": [],
  "thinBlockRangeReduction": 2,
  "thinBlockWeightReduction": 0.2,
  "liquidMufflingEnabled": true,
  "customLiquidBlocks": [],
  "liquidBlockRangeReduction": 1,
  "liquidBlockWeightReduction": 0.1,
  "fovOverrides": [
    "minecraft:spider, 360.0, 360.0",
    "minecraft:cave_spider, 360.0, 360.0",
    "minecraft:phantom, 200.0, 280.0",
    "minecraft:vex, 200.0, 280.0",
    "minecraft:allay, 200.0, 280.0",
    "minecraft:bat, 20.0, 20.0",
    "minecraft:parrot, 200.0, 280.0",
    "minecraft:ghast, 200.0, 280.0",
    "minecraft:blaze, 200.0, 280.0",
    "minecraft:axolotl, 270.0, 90.0",
    "minecraft:camel, 270.0, 90.0",
    "minecraft:chicken, 270.0, 90.0",
    "minecraft:cow, 270.0, 90.0",
    "minecraft:donkey, 270.0, 90.0",
    "minecraft:goat, 270.0, 90.0",
    "minecraft:horse, 270.0, 90.0",
    "minecraft:mule, 270.0, 90.0",
    "minecraft:mooshroom, 270.0, 90.0",
    "minecraft:panda, 270.0, 90.0",
    "minecraft:pig, 270.0, 90.0",
    "minecraft:rabbit, 270.0, 90.0",
    "minecraft:sheep, 270.0, 90.0",
    "minecraft:sniffer, 270.0, 90.0",
    "minecraft:strider, 270.0, 90.0",
    "minecraft:turtle, 270.0, 90.0",
    "minecraft:villager, 270.0, 90.0",
    "minecraft:wandering_trader, 270.0, 90.0",
    "minecraft:slime, 270.0, 120.0",
    "minecraft:magma_cube, 270.0, 120.0",
    "minecraft:cod, 300.0, 100.0",
    "minecraft:pufferfish, 300.0, 100.0",
    "minecraft:salmon, 300.0, 100.0",
    "minecraft:squid, 300.0, 100.0",
    "minecraft:glow_squid, 300.0, 100.0",
    "minecraft:tadpole, 300.0, 100.0",
    "minecraft:tropical_fish, 300.0, 100.0",
    "minecraft:cat, 140.0, 140.0",
    "minecraft:ocelot, 140.0, 140.0",
    "minecraft:wolf, 140.0, 140.0",
    "minecraft:polar_bear, 140.0, 140.0",
    "minecraft:fox, 140.0, 140.0",
    "minecraft:frog, 140.0, 140.0",
    "minecraft:zombie, 200.0, 135.0",
    "minecraft:husk, 200.0, 135.0",
    "minecraft:drowned, 200.0, 135.0",
    "minecraft:skeleton, 200.0, 135.0",
    "minecraft:stray, 200.0, 135.0",
    "minecraft:pillager, 200.0, 135.0",
    "minecraft:vindicator, 200.0, 135.0",
    "minecraft:evoker, 200.0, 135.0",
    "minecraft:witch, 200.0, 135.0",
    "minecraft:piglin, 200.0, 135.0",
    "minecraft:piglin_brute, 200.0, 135.0",
    "minecraft:iron_golem, 200.0, 135.0",
    "minecraft:creeper, 90.0, 90.0",
    "minecraft:enderman, 180.0, 240.0",
    "minecraft:guardian, 320.0, 180.0",
    "minecraft:elder_guardian, 320.0, 180.0",
    "minecraft:ravager, 160.0, 100.0",
    "minecraft:hoglin, 160.0, 100.0",
    "minecraft:zoglin, 160.0, 100.0",
    "minecraft:shulker, 270.0, 45.0"
  ],
  "fovExclusionList": [],
  "stealthCheckInterval": 30,
  "targetLossGracePeriodTicks": 60,
  "standingDetectionRange": 32.0,
  "standingDetectionRangeCamouflage": 1.0,
  "sneakDetectionRange": 12.0,
  "sneakDetectionRangeCamouflage": 1.0,
  "crawlDetectionRange": 4.0,
  "crawlDetectionRangeCamouflage": 1.0,
  "invisibilityStealthFactor": 0.1,
  "neutralLightLevel": 7.0,
  "lightLevelSensitivity": 0.8,
  "minLightFactor": 0.2,
  "maxLightFactor": 3.0,
  "enableHeldItemPenalty": true,
  "heldItemPenaltyFactor": 1.1,
  "enableEnchantmentPenalty": true,
  "armorEnchantmentPenaltyFactor": 1.15,
  "heldItemEnchantmentPenaltyFactor": 1.15,
  "rainStealthFactor": 0.8,
  "thunderStealthFactor": 0.6,
  "movementThreshold": 0.003,
  "movementStealthPenalty": 1.2,
  "stationaryStealthBonusFactor": 0.8,
  "camouflageDistanceScaling": true,
  "camouflageDistanceMax": 16.0,
  "camouflageDistanceMinEffectiveness": 0.3,
  "camouflageMovementPenalty": true,
  "camouflageSprintingPenalty": 0.4,
  "camouflageWalkingPenalty": 0.15,
  "camouflageColorSimilarityThreshold": 70,
  "camouflageSets": [
    "F9FFFE;minecraft:leather_helmet;minecraft:leather_chestplate;minecraft:leather_leggings;minecraft:leather_boots",
    "F9801D;minecraft:leather_helmet;minecraft:leather_chestplate;minecraft:leather_leggings;minecraft:leather_boots",
    "C74EBD;minecraft:leather_helmet;minecraft:leather_chestplate;minecraft:leather_leggings;minecraft:leather_boots",
    "3AB3DA;minecraft:leather_helmet;minecraft:leather_chestplate;minecraft:leather_leggings;minecraft:leather_boots",
    "FED83D;minecraft:leather_helmet;minecraft:leather_chestplate;minecraft:leather_leggings;minecraft:leather_boots",
    "80C71F;minecraft:leather_helmet;minecraft:leather_chestplate;minecraft:leather_leggings;minecraft:leather_boots",
    "F38BAA;minecraft:leather_helmet;minecraft:leather_chestplate;minecraft:leather_leggings;minecraft:leather_boots",
    "474F52;minecraft:leather_helmet;minecraft:leather_chestplate;minecraft:leather_leggings;minecraft:leather_boots",
    "9D9D97;minecraft:leather_helmet;minecraft:leather_chestplate;minecraft:leather_leggings;minecraft:leather_boots",
    "169C9C;minecraft:leather_helmet;minecraft:leather_chestplate;minecraft:leather_leggings;minecraft:leather_boots",
    "8932B8;minecraft:leather_helmet;minecraft:leather_chestplate;minecraft:leather_leggings;minecraft:leather_boots",
    "3C44AA;minecraft:leather_helmet;minecraft:leather_chestplate;minecraft:leather_leggings;minecraft:leather_boots",
    "835432;minecraft:leather_helmet;minecraft:leather_chestplate;minecraft:leather_leggings;minecraft:leather_boots",
    "5E7C16;minecraft:leather_helmet;minecraft:leather_chestplate;minecraft:leather_leggings;minecraft:leather_boots",
    "B02E26;minecraft:leather_helmet;minecraft:leather_chestplate;minecraft:leather_leggings;minecraft:leather_boots",
    "1D1D21;minecraft:leather_helmet;minecraft:leather_chestplate;minecraft:leather_leggings;minecraft:leather_boots"
  ],
  "enableVoiceChatIntegration": true,
  "voiceChatWhisperRange": 8,
  "voiceChatNormalRange": 32,
  "voiceChatWeight": 50.0,
  "voiceChatDbThresholdMap": [
    "110:2.0",
    "90:1.8",
    "75:1.5",
    "50:1.0",
    "30:0.7",
    "10:0.3",
    "0:0.05"
  ],
  "enablePointBlankIntegration": true,
  "pointblankReloadRange": 9.0,
  "pointblankReloadWeight": 9,
  "pointblankShootRange": 128.0,
  "pointblankBaseAttachmentReduction": 0.0,
  "pointblankShootWeight": 10,
  "gunshotBaseDetectionRange": 128.0,
  "gunshotDetectionDurationTicks": 60,
  "pointblankGunShootRanges": [
    "pointblank:glock17;128.0",
    "pointblank:glock18;128.0",
    "pointblank:m9;128.0",
    "pointblank:m1911a1;128.0",
    "pointblank:tti_viper;128.0",
    "pointblank:p30l;128.0",
    "pointblank:mk23;128.0",
    "pointblank:deserteagle;140.0",
    "pointblank:rhino;138.0",
    "pointblank:m4a1;118.0",
    "pointblank:m4a1mod1;118.0",
    "pointblank:star15;90.0",
    "pointblank:m4sopmodii;118.0",
    "pointblank:m16a1;90.0",
    "pointblank:hk416;118.0",
    "pointblank:scarl;72.0",
    "pointblank:xm7;118.0",
    "pointblank:g36c;132.0",
    "pointblank:g36k;132.0",
    "pointblank:aug;118.0",
    "pointblank:g41;118.0",
    "pointblank:ak74;128.0",
    "pointblank:ak12;128.0",
    "pointblank:an94;128.0",
    "pointblank:ar57;128.0",
    "pointblank:xm29;128.0",
    "pointblank:mp5;128.0",
    "pointblank:mp7;128.0",
    "pointblank:ro635;119.0",
    "pointblank:ump45;128.0",
    "pointblank:vector;90.0",
    "pointblank:p90;128.0",
    "pointblank:m950;128.0",
    "pointblank:tmp;128.0",
    "pointblank:sl8;128.0",
    "pointblank:mk14ebr;128.0",
    "pointblank:uar10;156.0",
    "pointblank:g3;128.0",
    "pointblank:wa2000;128.0",
    "pointblank:xm3;128.0",
    "pointblank:c14;128.0",
    "pointblank:l96a1;128.0",
    "pointblank:ballista;128.0",
    "pointblank:gm6lynx;128.0",
    "pointblank:m590;128.0",
    "pointblank:m870;128.0",
    "pointblank:spas12;128.0",
    "pointblank:m1014;128.0",
    "pointblank:citoricxs;128.0",
    "pointblank:hs12;128.0",
    "pointblank:lamg;128.0",
    "pointblank:mk48;128.0",
    "pointblank:m249;128.0",
    "pointblank:m32mgl;128.0",
    "pointblank:smaw;128.0",
    "pointblank:at4;128.0",
    "pointblank:javelin;200.0",
    "pointblank:m134minigun;156.0",
    "pointblank:aughbar;128.0",
    "pointblank:aa12;128.0",
    "pointblank:ak47;128.0"
  ],
  "pointblankAttachmentSoundReductions": [
    "pointblank:ar_suppressor;40.0",
    "pointblank:ar_suppressor_tan;40.0",
    "pointblank:xm7_suppressor;40.0",
    "pointblank:ak_suppressor;40.0",
    "pointblank:smg_suppressor;40.0",
    "pointblank:rf_suppressor;40.0",
    "pointblank:hp_suppressor;40.0",
    "pointblank:sg_suppressor;40.0"
  ],
  "pointblankMuzzleFlashReductions": [
    "pointblank:ar_suppressor;90.0",
    "pointblank:ar_suppressor_tan;90.0",
    "pointblank:xm7_suppressor;90.0",
    "pointblank:ak_suppressor;90.0",
    "pointblank:smg_suppressor;90.0",
    "pointblank:rf_suppressor;90.0",
    "pointblank:hp_suppressor;90.0",
    "pointblank:sg_suppressor;90.0"
  ],
  "specialMobProfilesRaw": [
    "GreedyGoblin;minecraft:piglin;;minecraft:block.chest.open:30.0:2.5,minecraft:entity.player.death:50.0:3.0;standing:40.0,sneaking:20.0,crawling:10.0",
    "FastZombie;minecraft:zombie;{IsAlpha:1b};minecraft:entity.player.hurt:25.0:2.0;standing:60.0,sneaking:30.0,crawling:10.0"
  ],
  "specialPlayerProfilesRaw": [
    "FelineOrigin;{cardinal_components:{\"origins:origin\":{OriginLayers:[{Layer:\"origins:origin\",Origin:\"origins:feline\"}]}}};standing:24.0,sneaking:10.0,crawling:3.0"
  ],
  "enableBlockBreaking": false,
  "blockBreakTimeMultiplier": 1.0,
  "blockBreakToolOnly": false,
  "blockBreakProperToolOnly": false,
  "blockBreakProperToolRequired": false,
  "blockBreakMaxY": 255,
  "blockBreakBlacklistTileEntities": true,
  "blockBreakListAsWhitelist": false,
  "blockBreakBlockList": [],
  "enableTeleportToSound": false,
  "teleportChance": 0.35,
  "teleportCooldownTicks": 300,
  "teleportCanTeleportTag": "enhancedai:mobs/teleport_to_target/can_teleport",
  "teleportCanBeTeleportedTag": "enhancedai:mobs/teleport_to_target/can_be_teleported",
  "enablePickUpAndThrowToSound": false,
  "pickUpChance": 0.05,
  "pickUpCooldownTicks": 600,
  "pickUpMinDistanceToPickUp": 5,
  "pickUpMaxDistanceToThrow": 24,
  "pickUpSpeedModifier": 1.25,
  "pickUpCanPickUpTag": "enhancedai:mobs/pick_up_and_throw/can_pick_up",
  "pickUpCanBePickedUpTag": "enhancedai:mobs/pick_up_and_throw/can_be_picked_up",
  "enableXrayTargeting": false,
  "xrayApplyTag": "enhancedai:mobs/targeting/apply_xray",
  "xrayRequireBetterNearby": false,
  "xrayBetterNearbyTag": "enhancedai:mobs/targeting/better_nearby_targeting",
  "xrayMinRange": 16,
  "xrayMaxRange": 24,
  "xrayChance": 0.5,
  "nonBlockingVisionAllowList": []
}